LICENSE
MANIFEST.in
README.md
setup.py
dictmentor/__init__.py
dictmentor/base.py
dictmentor/extensions.py
dictmentor/types.py
dictmentor/utils.py
dictmentor/validator.py
dictmentor.egg-info/PKG-INFO
dictmentor.egg-info/SOURCES.txt
dictmentor.egg-info/dependency_links.txt
dictmentor.egg-info/requires.txt
dictmentor.egg-info/top_level.txt