Metadata-Version: 2.1
Name: dictmentor
Version: 0.2.1
Summary: A python dictionary augmentation utility
Home-page: https://github.com/HazardDede/dictmentor
Author: d.muth
Author-email: d.muth@gmx.net
License: MIT
Project-URL: Documentation, https://github.com/HazardDede/dictmentor/blob/master/README.md
Project-URL: Source, https://github.com/HazardDede/dictmentor/
Project-URL: Tracker, https://github.com/HazardDede/dictmentor/issues
Keywords: dict dictionary augmentation augment style
Platform: UNKNOWN
Classifier: Development Status :: 3 - Alpha
Classifier: Intended Audience :: Developers
Classifier: Topic :: Software Development :: Libraries
Classifier: License :: OSI Approved :: MIT License
Classifier: Programming Language :: Python :: 3.4
Classifier: Programming Language :: Python :: 3.5
Classifier: Programming Language :: Python :: 3.6
Classifier: Programming Language :: Python :: 3.7
Requires-Python: >=3.4
